[{"name":"MK2","email":"mk@again.com","title":"This page is finished","message":"This page didn&#x27;t reload and worked as an SPA using jquery."},{"name":"MK1","email":"mkagain@test.com","title":"Title of the message","message":"Message body content"},{"name":"Manjunath","email":"test@test.com","title":"REST Title Test","message":"Message sent via REST"},{"name":"My Name","email":"test@test.com","title":"This was very nice","message":"Add more!"},{"name":"Frank","email":"frank-smith@gmail.com","title":"Best Meetup Ever","message":"I really love this meetup. Please don't let it end."},{"name":"Jane","email":"jane-miller@gmail.com","title":"Meeting Time","message":"Would you consider moving the meeting time 30 minutes to about 6pm. It's tough to make it to the meetings on time right after work."},{"name":"Roy","email":"roy-jones@gmail.com","title":"Great Speaker","message":"I really enjoyed the speaker this month. Would love to hear another presentation."}]